Workbook

Sheet Expense Forecast
A1: AeroSense Bio Expense Forecast (Biomedical R&D Startup / Year 1, Annual Basis) Unit: NT$ (New Taiwan Dollar)
A2: Item No. | B2: Account Category | C2: Line Item | D2: NT$ (Annual) | E2: Notes
A3: 1 | B3: Share Capital | C3: Company Share Capital | D3: 1000000 | E3: Founders' paid-in capital (consistent with founders' contribution in the "Equity Plan" sheet)
A4: 2 | B4: Startup Costs | C4: Company Registration | D4: 3000
A5: 3 | C5: Accounting Agency & Bookkeeping Fees | D5: 30000
A6: 4 | C6: Renovation / Fit-out Costs | D6: 0 | E6: Fill in per team needs
A7: 5 | C7: Rental Deposit | D7: 20000
A8: 6 | C8: Office Desks & Chairs | D8: 10000
A9: 7 | C9: Computers / Lab Computer Equipment | D9: 50000 | E9: 2 units × 25,000
A10: 8 | C10: Miscellaneous | D10: 0
C11: Subtotal (Startup Costs, Items 2–8) | D11: =SUM(D4:D10) -> 113000
A12: 9 | B12: Fixed Costs | C12: Office Rent/Year | D12: 120000 | E12: 10,000 × 12 (may be lower if joining an incubator)
A13: 10 | C13: Bookkeeper Fees/Year | D13: 42000 | E13: 3,500 × 12
A14: 11 | C14: Registered Address Fee/Year | D14: 36000 | E14: 3,000 × 12
A15: 12 | C15: Number of Employees | D15: 3 | E15: Three founders (adjustable)
C16: Average Monthly Salary (NT$) | D16: 40000 | E16: Early-stage founder salary (adjustable)
A17: 13 | C17: Personnel Costs/Year | D17: =(D16*12*1.25+D16*2)*D15 -> 2040000 | E17: Includes labor/health insurance employer contribution (1.25×) + year-end bonus (2 months)
C18: Subtotal (Fixed Costs, Items 9–11, 13) | D18: =D12+D13+D14+D17 -> 2238000
A19: 14 | B19: Variable Costs | C19: R&D Equipment | D19: 300000 | E19: Estimated instrument center / equipment usage fees
A20: 15 | C20: Biological Reagents & Cell Culture Consumables | D20: 240000 | E20: 20,000 × 12 (cells, plasmids, GCaMP, etc.)
A21: 16 | C21: Utilities (Water & Electricity) | D21: 60000 | E21: 5,000 × 12
A22: 17 | C22: Travel Expenses | D22: 60000 | E22: 5,000 × 12
A23: 18 | C23: Company Email Account | D23: 5500
A24: 19 | C24: IP & Regulatory Consulting Fees | D24: 60000 | E24: Early-stage patent/regulatory costs (adjustable)
A25: 20 | C25: Miscellaneous / Office Supplies | D25: 0
A26: 21 | C26: Employee Training Costs | D26: 0
A27: 22 | C27: Interest Expense | D27: 0
C28: Subtotal (Variable Costs, Items 14–22) | D28: =SUM(D19:D27) -> 725500
A29: 23 | B29: Taxes | C29: Corporate Income Tax | D29: 0 | E29: No profit in early stage
A30: 24 | C30: Business Tax | D30: 0
A31: 25 | C31: Undistributed Earnings Tax | D31: 0
C32: Subtotal (Taxes, Items 23–25) | D32: =SUM(D29:D31) -> 0
C33: Total Annual Expenses (Excl. Share Capital) | D33: =D11+D18+D28+D32 -> 3076500
A35: ※ Blue text = assumptions you may edit; black text = auto-calculated by formula. After editing blue cells, please recalculate in Excel.

Sheet Burn Rate Forecast
A1: AeroSense Bio | 18-Month Burn Rate Forecast (NTD)
A2: Starting Capital (Founders' Equity + Angel Round Paid-in) | B2: 3000000
A3: Monthly Revenue (Year 1 Assumption) | B3: 0
A5: Month | C5: 1 | D5: 2 | E5: 3 | F5: 4 | G5: 5 | H5: 6 | I5: 7 | J5: 8 | K5: 9 | L5: 10 | M5: 11 | N5: 12 | O5: 13 | P5: 14 | Q5: 15 | R5: 16 | S5: 17 | T5: 18
A6: Initial Cash (Start of Month) | C6: =$B$2 -> 3000000 | D6: =C6-C11+C7 -> 2640041.7 | E6: =D6-D11+D7 -> 2393083.3 | F6: =E6-E11+E7 -> 2146125 | G6: =F6-F11+F7 -> 1899166.7 | H6: =G6-G11+G7 -> 1652208.3 | I6: =H6-H11+H7 -> 1405250 | J6: =I6-I11+I7 -> 1158291.7 | K6: =J6-J11+J7 -> 911333.33 | ... T6: =S6-S11+S7 -> -1311291.7
A7: Income/Month | C7: =$B$3 -> 0 | D7: =$B$3 -> 0 | E7: =$B$3 -> 0 | F7: =$B$3 -> 0 | G7: =$B$3 -> 0 | H7: =$B$3 -> 0 | I7: =$B$3 -> 0 | J7: =$B$3 -> 0 | ... T7: =$B$3 -> 0
A8: One-Time Expenses (Startup Costs) | C8: ='Expense Forecast'!$D$11 -> 113000 | D8: 0 | E8: 0 | F8: 0 | G8: 0 | H8: 0 | I8: 0 | J8: 0 | K8: 0 | L8: 0 | M8: 0 | N8: 0 | O8: 0 | P8: 0 | Q8: 0 | R8: 0 | S8: 0 | T8: 0
A9: Fixed Costs/Month | C9: ='Expense Forecast'!$D$18/12 -> 186500 | D9: ='Expense Forecast'!$D$18/12 -> 186500 | E9: ='Expense Forecast'!$D$18/12 -> 186500 | F9: ='Expense Forecast'!$D$18/12 -> 186500 | G9: ='Expense Forecast'!$D$18/12 -> 186500 | H9: ='Expense Forecast'!$D$18/12 -> 186500 | I9: ='Expense Forecast'!$D$18/12 -> 186500 | J9: ='Expense Forecast'!$D$18/12 -> 186500 | ... T9: ='Expense Forecast'!$D$18/12 -> 186500
A10: Variable Costs/Month | C10: ='Expense Forecast'!$D$28/12 -> 60458.333 | D10: ='Expense Forecast'!$D$28/12 -> 60458.333 | E10: ='Expense Forecast'!$D$28/12 -> 60458.333 | F10: ='Expense Forecast'!$D$28/12 -> 60458.333 | G10: ='Expense Forecast'!$D$28/12 -> 60458.333 | H10: ='Expense Forecast'!$D$28/12 -> 60458.333 | I10: ='Expense Forecast'!$D$28/12 -> 60458.333 | J10: ='Expense Forecast'!$D$28/12 -> 60458.333 | ... T10: ='Expense Forecast'!$D$28/12 -> 60458.333
A11: Gross Burn (Total Expenses) | C11: =C8+C9+C10 -> 359958.33 | D11: =D8+D9+D10 -> 246958.33 | E11: =E8+E9+E10 -> 246958.33 | F11: =F8+F9+F10 -> 246958.33 | G11: =G8+G9+G10 -> 246958.33 | H11: =H8+H9+H10 -> 246958.33 | I11: =I8+I9+I10 -> 246958.33 | J11: =J8+J9+J10 -> 246958.33 | ... T11: =T8+T9+T10 -> 246958.33
A12: Net Burn (Expenses − Income) | C12: =C11-C7 -> 359958.33 | D12: =D11-D7 -> 246958.33 | E12: =E11-E7 -> 246958.33 | F12: =F11-F7 -> 246958.33 | G12: =G11-G7 -> 246958.33 | H12: =H11-H7 -> 246958.33 | I12: =I11-I7 -> 246958.33 | J12: =J11-J7 -> 246958.33 | ... T12: =T11-T7 -> 246958.33
A13: Burn Rate (Monthly Expenses / Initial Cash) | C13: =IFERROR(C11/C6,"") -> 0.11998611 | D13: =IFERROR(D11/D6,"") -> 0.093543347 | E13: =IFERROR(E11/E6,"") -> 0.10319671 | F13: =IFERROR(F11/F6,"") -> 0.11507174 | G13: =IFERROR(G11/G6,"") -> 0.1300351 | H13: =IFERROR(H11/H6,"") -> 0.14947167 | I13: =IFERROR(I11/I6,"") -> 0.17573979 | J13: =IFERROR(J11/J6,"") -> 0.21320911 | ... T13: =IFERROR(T11/T6,"") -> -0.18833212
A14: Runway (Months Remaining) | C14: =IFERROR(C6/C11,"") -> 8.334298 | D14: =IFERROR(D6/D11,"") -> 10.690231 | E14: =IFERROR(E6/E11,"") -> 9.6902311 | F14: =IFERROR(F6/F11,"") -> 8.6902311 | G14: =IFERROR(G6/G11,"") -> 7.6902311 | H14: =IFERROR(H6/H11,"") -> 6.6902311 | I14: =IFERROR(I6/I11,"") -> 5.6902311 | J14: =IFERROR(J6/J11,"") -> 4.6902311 | ... T14: =IFERROR(T6/T11,"") -> -5.3097689
A16: ※ Initial cash turning red = funds depleted; ideal runway is 12–18 months. Fixed/variable costs (green text) are linked to the "Expense Forecast" sheet.

Sheet 3-Year P&L
A1: AeroSense Bio | 3-Year P&L Forecast (Base Case, NTD)
A2: Item | B2: Year 1 | C2: Year 2 | D2: Year 3 | E2: Notes
A3: Devices Sold This Year (Units) | B3: 3 | C3: 12 | D3: 35 | E3: Beachhead market installs (assumption)
A4: Device Unit Price (NT$/Unit) | B4: 120000 | C4: 120000 | D4: 110000 | E4: Razor pricing; slight decline after mass production
A5: Cumulative Installed Units | B5: =B3 -> 3 | C5: =B5+C3 -> 15 | D5: =C5+D3 -> 50 | E5: Determines cartridge subscription base
A6: Cartridge Monthly Fee (NT$/Unit·Month) | B6: 4000 | C6: 4000 | D6: 4500 | E6: Razor blade model; recurring revenue
A7: Software/Data & Custom Services Revenue | B7: 0 | C7: 300000 | D7: 1200000 | E7: NRE/subscription (assumption)
A9: Device Revenue | B9: =B3*B4 -> 360000 | C9: =C3*C4 -> 1440000 | D9: =D3*D4 -> 3850000 | E9: Units sold × unit price
A10: Cartridge Subscription Revenue | B10: =B5*B6*12 -> 144000 | C10: =C5*C6*12 -> 720000 | D10: =D5*D6*12 -> 2700000 | E10: Cumulative installs × monthly fee × 12
A11: Software/Services Revenue | B11: =B7 -> 0 | C11: =C7 -> 300000 | D11: =D7 -> 1200000
A12: Total Operating Revenue | B12: =B9+B10+B11 -> 504000 | C12: =C9+C10+C11 -> 2460000 | D12: =D9+D10+D11 -> 7750000
A13: Gross Margin (Assumption) | B13: 0.45 | C13: 0.55 | D13: 0.6 | E13: Improves with scale and receptor-library reuse
A14: Cost of Goods Sold | B14: =B12*(1-B13) -> 277200 | C14: =C12*(1-C13) -> 1107000 | D14: =D12*(1-D13) -> 3100000 | E14: Hardware BOM + cartridge production
A15: Gross Profit | B15: =B12-B14 -> 226800 | C15: =C12-C14 -> 1353000 | D15: =D12-D14 -> 4650000
A16: Personnel Expenses | B16: 2400000 | C16: 3600000 | D16: 5400000 | E16: Team expansion (assumption)
A17: R&D Expenses | B17: 1200000 | C17: 1800000 | D17: 2400000 | E17: Receptor/hardware R&D
A18: Operations & Other Expenses | B18: 600000 | C18: 900000 | D18: 1200000 | E18: Rent, admin, marketing, IP
A19: Total Operating Expenses | B19: =SUM(B16:B18) -> 4200000 | C19: =SUM(C16:C18) -> 6300000 | D19: =SUM(D16:D18) -> 9000000
A20: Operating Profit/Loss | B20: =B15-B19 -> -3973200 | C20: =C15-C19 -> -4947000 | D20: =D15-D19 -> -4350000
A21: Operating Margin | B21: =IFERROR(B20/B12,"") -> -7.8833333 | C21: =IFERROR(C20/C12,"") -> -2.0109756 | D21: =IFERROR(D20/D12,"") -> -0.56129032
A23: ※ Blue text is an adjustable assumption; this table is the base case — a conservative and an optimistic version are recommended as well. Figures are illustrative only; calibrate against actual pilot quotes.

Sheet Equity Plan
A1: AeroSense Bio Equity Plan (Centered on Three Founders) Unit: NT$ (New Taiwan Dollar)
A2: STEP 1–6: Fill in the yellow assumption cells below; the equity table will automatically calculate share counts, ownership %, valuation, and paid-in amount for each round.
A3: STEP 1 Total Original Shareholder Shares (Three Founders) | E3: 100000
A4: STEP 2 Original Shareholder Issue Price per Share | E4: 10
A5: STEP 3 Total Technology Shares | E5: 30000
A6: STEP 3 Technology Share Issue Price per Share | E6: 10
A7: STEP 4 Institution's Share of Technology Equity (%) | E7: 0.2
A8: STEP 5 Total Angel Round Shares | E8: 40000
A9: STEP 5 Angel Round Issue Price per Share | E9: 50
A10: STEP 6 Total Round 1 Shares | E10: 50000
A11: STEP 6 Round 1 Issue Price per Share | E11: 120
A12: Number of Founders | E12: 3
A13: Par Value (NT$/Share) | E13: 10
A16: Item | B16: Inventor Team Contribution | D16: Technology Shares | F16: Angel Round | H16: Round 1
B17: Shares | C17: % Ownership | D17: Shares | E17: % Ownership | F17: Shares | G17: % Ownership | H17: Shares | I17: % Ownership
A18: Original Shareholders (Founders) | B18: =$E$3 -> 100000 | C18: =IFERROR(B18/B$24,"") -> 1 | D18: =$E$3 -> 100000 | E18: =IFERROR(D18/D$24,"") -> 0.76923077 | F18: =$E$3 -> 100000 | G18: =IFERROR(F18/F$24,"") -> 0.58823529 | H18: =$E$3 -> 100000 | I18: =IFERROR(H18/H$24,"") -> 0.45454545
A19: Technology Shares | B19: 0 | C19: =IFERROR(B19/B$24,"") -> 0 | D19: =$E$5 -> 30000 | E19: =IFERROR(D19/D$24,"") -> 0.23076923 | F19: =$E$5 -> 30000 | G19: =IFERROR(F19/F$24,"") -> 0.17647059 | H19: =$E$5 -> 30000 | I19: =IFERROR(H19/H$24,"") -> 0.13636364
A20: Institution's Technology Shares | B20: 0 | C20: =IFERROR(B20/B$24,"") -> 0 | D20: =$E$5*$E$7 -> 6000 | E20: =IFERROR(D20/D$24,"") -> 0.046153846 | F20: =$E$5*$E$7 -> 6000 | G20: =IFERROR(F20/F$24,"") -> 0.035294118 | H20: =$E$5*$E$7 -> 6000 | I20: =IFERROR(H20/H$24,"") -> 0.027272727
A21: Inventor Team's Technology Shares | B21: 0 | C21: =IFERROR(B21/B$24,"") -> 0 | D21: =$E$5*(1-$E$7) -> 24000 | E21: =IFERROR(D21/D$24,"") -> 0.18461538 | F21: =$E$5*(1-$E$7) -> 24000 | G21: =IFERROR(F21/F$24,"") -> 0.14117647 | H21: =$E$5*(1-$E$7) -> 24000 | I21: =IFERROR(H21/H$24,"") -> 0.10909091
A22: Angel Round | B22: 0 | C22: =IFERROR(B22/B$24,"") -> 0 | D22: 0 | E22: =IFERROR(D22/D$24,"") -> 0 | F22: =$E$8 -> 40000 | G22: =IFERROR(F22/F$24,"") -> 0.23529412 | H22: =$E$8 -> 40000 | I22: =IFERROR(H22/H$24,"") -> 0.18181818
A23: Round 1 | B23: 0 | C23: =IFERROR(B23/B$24,"") -> 0 | D23: 0 | E23: =IFERROR(D23/D$24,"") -> 0 | F23: 0 | G23: =IFERROR(F23/F$24,"") -> 0 | H23: =$E$10 -> 50000 | I23: =IFERROR(H23/H$24,"") -> 0.22727273
A24: Total Shares | B24: =B18+B19+B22+B23 -> 100000 | C24: =1 -> 1 | D24: =D18+D19+D22+D23 -> 130000 | E24: =1 -> 1 | F24: =F18+F19+F22+F23 -> 170000 | G24: =1 -> 1 | H24: =H18+H19+H22+H23 -> 220000 | I24: =1 -> 1
A25: Issue Price/Share | B25: =$E$4 -> 10 | D25: =$E$6 -> 10 | F25: =$E$9 -> 50 | H25: =$E$11 -> 120
A26: Share Capital (Par Value × Total Shares) | B26: =B24*$E$13 -> 1000000 | D26: =D24*$E$13 -> 1300000 | F26: =F24*$E$13 -> 1700000 | H26: =H24*$E$13 -> 2200000
A27: Total Valuation (Total Shares × Round Price) | B27: =B24*$E$4 -> 1000000 | D27: =D24*$E$6 -> 1300000 | F27: =F24*$E$9 -> 8500000 | H27: =H24*$E$11 -> 26400000
A28: Paid-in / Valuation Amount per Round | B28: =$E$3*$E$4 -> 1000000 | D28: =$E$5*$E$6 -> 300000 | F28: =$E$8*$E$9 -> 2000000 | H28: =$E$10*$E$11 -> 6000000
A29: Cumulative Paid-in Amount | B29: =B28 -> 1000000 | D29: =B28+D28 -> 1300000 | F29: =B28+D28+F28 -> 3300000 | H29: =B28+D28+F28+H28 -> 9300000
A30: ※ Technology shares are issued as in-kind (non-cash) technology valuation; the "Paid-in / Valuation Amount per Round" above includes this valuation amount. Cash fundraising is primarily via the Angel Round and Round 1.
A32: Three Founders' Shareholding (Post-Round-1 Dilution)
A33: Founder | B33: Shares Held | C33: % Ownership After Round 1 | D33: Notes
A34: Founder 1 | B34: =($E$3+$E$5*(1-$E$7))/$E$12 -> 41333.333 | C34: =IFERROR(B34/H$24,"") -> 0.18787879 | D34: Original shareholder shares + inventor team technology shares, split evenly (adjustable)
A35: Founder 2 | B35: =($E$3+$E$5*(1-$E$7))/$E$12 -> 41333.333 | C35: =IFERROR(B35/H$24,"") -> 0.18787879 | D35: Original shareholder shares + inventor team technology shares, split evenly (adjustable)
A36: Founder 3 | B36: =($E$3+$E$5*(1-$E$7))/$E$12 -> 41333.333 | C36: =IFERROR(B36/H$24,"") -> 0.18787879 | D36: Original shareholder shares + inventor team technology shares, split evenly (adjustable)
A37: Founders' Total | B37: =SUM(B34:B36) -> 124000 | C37: =IFERROR(B37/H$24,"") -> 0.56363636 | D37: Founding team's combined ownership percentage after Round 1
